shopscraper/__init__.py
shopscraper/api.py
shopscraper/headers.py
shopscraper/json_handler.py
shopscraper/prod_objs.py
shopscraper/py.typed
shopscraper/scraper.py
shopscraper-0.0.6.dist-info/LICENSE
shopscraper-0.0.6.dist-info/WHEEL
shopscraper-0.0.6.dist-info/METADATA
shopscraper-0.0.6.dist-info/RECORD
