Metadata-Version: 2.1
Name: shopscraper
Version: 0.0.6
Summary: ShopScraper is a thin python wrapper for Shopify webshop product APIs used to scrape information from online stores.
Home-page: https://github.com/philistino/shopscraper
Author: Philistino
Author-email: fphilistino@protonmail.com
Requires-Python: >=3.9,<3.11
Classifier: Programming Language :: Python :: 3
Classifier: Programming Language :: Python :: 3.10
Classifier: Programming Language :: Python :: 3.9
Requires-Dist: pydantic (>=1.9.0,<2.0.0)
Requires-Dist: requests (>=2.27.1,<3.0.0)
Project-URL: Documentation, https://philistino.github.io/shopscraper/
Project-URL: Repository, https://github.com/philistino/shopscraper
